README.rst
overview-create-document-set
overview-upload
overview-upload-csv
setup.py
overview_upload/__init__.py
overview_upload/_document_set.py
overview_upload/_metadata.py
overview_upload/_upload.py
overview_upload.egg-info/PKG-INFO
overview_upload.egg-info/SOURCES.txt
overview_upload.egg-info/dependency_links.txt
overview_upload.egg-info/requires.txt
overview_upload.egg-info/top_level.txt