Metadata-Version: 1.1
Name: overview-upload
Version: 0.9.9
Summary: Upload documents to Overview web server
Home-page: https://github.com/overview/overview-upload-directory
Author: UNKNOWN
Author-email: UNKNOWN
License: UNKNOWN
Platform: UNKNOWN
Classifier: License :: OSI Approved :: GNU Affero General Public License v3
Classifier: Intended Audience :: Developers
Classifier: Programming Language :: Python
Classifier: Programming Language :: Python :: 3
Classifier: Programming Language :: Python :: 3.6
